[   {
        "A1":"¿Qué tipo de operaciones puedo hacer en Actio Capital?",
    },
    {
        "pregunta":" ¿Cuánto tiempo tardan las transferencias a cuentas del mismo titular y a terceros, en otros bancos?",
    },
    {
        "pregunta":"¿Cuánto tiempo tardan los pagos de tarjetas de crédito del mismo titular y de terceros en otros bancos?",
    },
    {
        "pregunta":"¿Cuánto tiempo tardan en reflejarse los pagos CANTV y cuál es el horario para realizar esta operación?",
    },
    {
        "pregunta":"¿Qué condiciones aplican para la anulación de una tarjeta de crédito?",
    },
    {
        "pregunta":"¿Dónde puedo obtener más información si tengo otras preguntas?",
        "respuesta":"Comunícate sin costo alguno al teléfono (0212) XXX.XXXX"
    }
]